{"info": {"language": "Dansk", "ECTS": 5, "time": "E4B (fre 8-12)", "level": "Bachelor", "name": "Digital elektronik 1", "course_no": "02138"}, "evals": [{"time": "E-18-13", "N_responses": 44, "learning_answers": [20, 11, 11, 0, 2], "participation_answers": [12, 16, 11, 4, 1], "material_answers": [5, 18, 12, 6, 3], "clear_answers": [8, 11, 17, 3, 4], "connection_answers": [9, 17, 13, 3, 2], "worklevel_answers": [3, 5, 23, 10, 3], "prerequisite_answers": [0, 1, 30, 13, 0], "good_answers": [12, 16, 11, 4, 0]}, {"time": "E-17-13", "N_responses": 51, "learning_answers": [27, 18, 4, 1, 1], "participation_answers": [19, 27, 3, 2, 0], "material_answers": [8, 19, 11, 10, 3], "clear_answers": [9, 18, 17, 5, 2], "connection_answers": [13, 24, 10, 2, 2], "worklevel_answers": [2, 12, 22, 14, 1], "prerequisite_answers": [0, 2, 43, 6, 0], "good_answers": [20, 19, 7, 2, 3]}, {"time": "E-16-13", "N_responses": 65, "learning_answers": [27, 23, 11, 2, 2], "participation_answers": [19, 31, 8, 5, 1], "material_answers": [11, 24, 20, 7, 1], "clear_answers": [3, 19, 20, 18, 3], "connection_answers": [13, 21, 21, 6, 3], "worklevel_answers": [0, 7, 47, 9, 0], "prerequisite_answers": [0, 2, 52, 7, 2], "good_answers": [13, 30, 12, 6, 2]}, {"time": "E-15-13", "N_responses": 56, "learning_answers": [17, 21, 15, 2, 1], "participation_answers": [13, 24, 12, 6, 1], "material_answers": [10, 20, 19, 5, 2], "clear_answers": [7, 17, 23, 7, 2], "connection_answers": [8, 22, 20, 5, 1], "worklevel_answers": [0, 9, 28, 16, 3], "prerequisite_answers": [0, 2, 44, 7, 2], "good_answers": [13, 20, 20, 1, 2]}, {"time": "E-14-13", "N_responses": 40, "learning_answers": [12, 14, 7, 4, 2], "participation_answers": [10, 13, 7, 7, 2], "material_answers": [4, 14, 9, 8, 3], "clear_answers": [7, 7, 15, 6, 4], "connection_answers": [8, 14, 8, 4, 5], "worklevel_answers": [0, 5, 21, 13, 0], "prerequisite_answers": [0, 1, 31, 5, 1], "good_answers": [3, 16, 10, 4, 4]}, {"time": "E-13-13", "N_responses": 53, "learning_answers": [19, 21, 8, 5, 0], "participation_answers": [16, 21, 12, 4, 0], "material_answers": [8, 19, 13, 11, 2], "clear_answers": [7, 18, 17, 8, 3], "connection_answers": [13, 20, 15, 5, 0], "worklevel_answers": [0, 7, 29, 12, 4], "prerequisite_answers": [1, 1, 44, 7, 0], "good_answers": [9, 27, 11, 4, 2]}, {"time": "E-12-13", "N_responses": 40, "learning_answers": [15, 19, 4, 2, 0], "participation_answers": [8, 20, 6, 5, 1], "material_answers": [3, 21, 10, 4, 2], "clear_answers": [2, 15, 20, 2, 1], "connection_answers": [7, 17, 11, 4, 1], "worklevel_answers": [1, 6, 26, 5, 2], "prerequisite_answers": [0, 3, 34, 3, 0], "good_answers": [7, 20, 9, 3, 1]}, {"time": "E-11-13", "N_responses": 40, "learning_answers": [20, 16, 4, 0, 0], "participation_answers": [16, 17, 6, 1, 0], "material_answers": [6, 16, 8, 7, 3], "clear_answers": [7, 14, 14, 4, 1], "connection_answers": [12, 18, 5, 5, 0], "worklevel_answers": [4, 7, 23, 4, 2], "prerequisite_answers": [0, 1, 32, 4, 0], "good_answers": [15, 16, 6, 3, 0]}, {"time": "E-10-13", "N_responses": 33, "learning_answers": [13, 11, 4, 4, 1], "participation_answers": [9, 15, 3, 4, 2], "material_answers": [6, 11, 9, 5, 2], "clear_answers": [1, 13, 9, 8, 2], "connection_answers": [2, 18, 6, 7, 0], "worklevel_answers": [0, 8, 18, 5, 1], "prerequisite_answers": [0, 1, 25, 4, 2], "good_answers": [6, 11, 9, 5, 2]}], "eval_points": [{"time": "E-18-13", "learning": 3.0681818181818183, "worklevel": 2.1136363636363638, "good": 2.772727272727273, "N": 44}, {"time": "E-17-13", "learning": 3.3529411764705883, "worklevel": 2.0, "good": 3.0, "N": 51}, {"time": "E-16-13", "learning": 3.0923076923076924, "worklevel": 1.9692307692307693, "good": 2.646153846153846, "N": 65}, {"time": "E-15-13", "learning": 2.9107142857142856, "worklevel": 2.232142857142857, "good": 2.732142857142857, "N": 56}, {"time": "E-14-13", "learning": 2.7, "worklevel": 2.15, "good": 2.1, "N": 40}, {"time": "E-13-13", "learning": 3.018867924528302, "worklevel": 2.207547169811321, "good": 2.69811320754717, "N": 53}, {"time": "E-12-13", "learning": 3.175, "worklevel": 2.025, "good": 2.725, "N": 40}, {"time": "E-11-13", "learning": 3.4, "worklevel": 1.825, "good": 3.075, "N": 40}, {"time": "E-10-13", "learning": 2.9393939393939394, "worklevel": 1.9090909090909092, "good": 2.4242424242424243, "N": 33}], "grades": [{"time": "2019summer", "N_exam": 19, "N_passed": 13, "exam_avg": 4.1, "grade_dist": [1, 1, 5, 4, 2, 6, 0, 2]}, {"time": "2018winter", "N_exam": 93, "N_passed": 54, "exam_avg": 3.5, "grade_dist": [4, 11, 16, 15, 8, 27, 10, 0, 2, 2]}, {"time": "2017summer", "N_exam": 8, "N_passed": 3, "exam_avg": 2.6, "grade_dist": [0, 1, 2, 0, 0, 4, 1, 10]}, {"time": "2017winter", "N_exam": 88, "N_passed": 69, "exam_avg": 5.6, "grade_dist": [15, 14, 13, 16, 11, 17, 2, 3, 3]}, {"time": "2016summer", "N_exam": 32, "N_passed": 8, "exam_avg": 1.8, "grade_dist": [0, 1, 2, 5, 0, 9, 3, 0, 12, 1]}, {"time": "2016winter", "N_exam": 87, "N_passed": 72, "exam_avg": 6.3, "grade_dist": [8, 18, 31, 11, 4, 13, 1, 0, 1, 1, 12]}, {"time": "2015summer", "N_exam": 14, "N_passed": 12, "exam_avg": 6.1, "grade_dist": [1, 4, 4, 1, 2, 1, 1, 3]}, {"time": "2015winter", "N_exam": 116, "N_passed": 81, "exam_avg": 5.2, "grade_dist": [22, 12, 25, 12, 10, 26, 9, 11]}, {"time": "2014winter", "N_exam": 97, "N_passed": 71, "exam_avg": 5.0, "grade_dist": [11, 15, 22, 12, 11, 18, 8, 14]}, {"time": "2013winter", "N_exam": 84, "N_passed": 54, "exam_avg": 4.1, "grade_dist": [9, 9, 13, 14, 9, 23, 7, 11]}], "grade_percentile": 5.8061420345489445, "eval_percentiles": {"learning": 48.73217115689382, "worklevel": 48.01901743264659, "good": 37.955625990491285}, "composites": {"beer_points": 1.5258070629856588, "quality_points": 1.4590398365679267, "beer_percentiles": 12.291666666666666, "quality_percentiles": 9.270833333333334}}