{"info": {"language": "Engelsk", "ECTS": 5, "time": "Efter\u00e5r  eller  For\u00e5r", "level": "Kandidat", "name": "Interdisciplinary Design Project", "course_no": "11526"}, "evals": [{"time": "E-18-13", "N_responses": 3, "learning_answers": [3, 0, 0, 0, 0], "participation_answers": [3, 0, 0, 0, 0], "material_answers": [0, 2, 1, 0, 0], "clear_answers": [0, 0, 1, 2, 0], "connection_answers": [1, 1, 1, 0, 0], "worklevel_answers": [0, 0, 2, 0, 1], "prerequisite_answers": [0, 0, 3, 0, 0], "good_answers": [3, 0, 0, 0, 0]}], "eval_points": [{"time": "E-18-13", "learning": 10.0, "worklevel": 6.666666666666666, "good": 10.0, "N": 3}], "course_no": "11526", "grade_percentile": null, "eval_percentiles": {"learning": 96.79643146796431, "worklevel": 82.80616382806164, "good": 96.79643146796431}, "composites": {"beer_points": null, "quality_points": null, "beer_percentiles": null, "quality_percentiles": null}}