{"info": {"language": "English", "ECTS": 5, "time": "January", "level": "BSc", "name": "Environmental Engineering in low- and middle-income countries", "course_no": "12210"}, "evals": [{"time": "E-14-03", "N_responses": 21, "learning_answers": [14, 4, 3, 0, 0], "participation_answers": [18, 2, 1, 0, 0], "material_answers": [8, 9, 3, 1, 0], "clear_answers": [9, 8, 4, 0, 0], "connection_answers": [11, 8, 2, 0, 0], "worklevel_answers": [1, 0, 10, 10, 0], "prerequisite_answers": [0, 0, 20, 1, 0], "good_answers": [14, 3, 2, 2, 0]}], "eval_points": [{"time": "E-14-03", "learning": 8.80952380952381, "worklevel": 5.9523809523809526, "good": 8.452380952380953, "N": 21}], "course_no": "12210", "grade_percentile": null, "eval_percentiles": {"learning": 80.93368237347295, "worklevel": 69.15357766143106, "good": 74.12739965095986}, "composites": {"beer_points": null, "quality_points": null, "beer_percentiles": null, "quality_percentiles": null}}