{"info": {"language": "Engelsk", "ECTS": 5, "time": "E1B (tors 13-17)", "level": "Bachelor", "name": "Introduktion til genetiske metoder for ingeni\u00f8rer", "course_no": "25106"}, "evals": [{"time": "E-18-13", "N_responses": 15, "learning_answers": [9, 2, 1, 2, 1], "participation_answers": [5, 4, 5, 1, 0], "material_answers": [5, 4, 3, 3, 0], "clear_answers": [5, 5, 3, 2, 0], "connection_answers": [6, 4, 4, 1, 0], "worklevel_answers": [0, 4, 8, 3, 0], "prerequisite_answers": [1, 1, 11, 2, 0], "good_answers": [9, 3, 2, 1, 0]}, {"time": "E-17-13", "N_responses": 10, "learning_answers": [1, 1, 3, 3, 2], "participation_answers": [0, 4, 4, 2, 0], "material_answers": [1, 1, 5, 3, 0], "clear_answers": [1, 3, 3, 1, 2], "connection_answers": [2, 2, 2, 3, 1], "worklevel_answers": [1, 5, 4, 0, 0], "prerequisite_answers": [1, 2, 6, 0, 0], "good_answers": [1, 3, 1, 4, 1]}], "eval_points": [{"time": "E-18-13", "learning": 7.666666666666667, "worklevel": 4.833333333333333, "good": 8.333333333333334, "N": 15}, {"time": "E-17-13", "learning": 4.0, "worklevel": 3.25, "good": 4.75, "N": 10}], "grades": [{"time": "2017winter", "N_exam": 17, "N_passed": 17, "exam_avg": 8.1, "grade_dist": [4, 5, 4, 2, 2, 0, 0, 2]}], "course_no": "25106", "grade_percentile": 54.276315789473685, "eval_percentiles": {"learning": 49.31350114416476, "worklevel": 27.72692601067887, "good": 71.09077040427155}, "composites": {"beer_points": 6.2917518745739605, "quality_points": 6.881268197994177, "beer_percentiles": 70.34482758620689, "quality_percentiles": 73.79310344827586}}