{"info": {"language": "Engelsk", "ECTS": 5, "time": "Januar", "level": "Kandidat", "name": "Switch-Mode Str\u00f8mforsyning 2. Laboratoriekursus", "course_no": "31353"}, "course_no": "31353", "grade_percentile": 19.853836784409257, "eval_percentiles": {"learning": 97.15665236051503, "worklevel": 75.5901287553648, "good": 79.6137339055794}, "composites": {"beer_points": 4.49868073878628, "quality_points": 7.087827426810478, "beer_percentiles": 17.641843971631207, "quality_percentiles": 70.56737588652483}}