{"info": {"language": "Engelsk", "ECTS": 10, "time": "E2 (man 13-17, tors 8-12)", "level": "Kandidat", "name": "Vindm\u00f8ller, PV ogElektriske Energilagring drivetrains", "course_no": "31787"}, "course_no": "31787", "grade_percentile": 37.17328170377541, "eval_percentiles": {"learning": 24.898621248986213, "worklevel": 57.50202757502028, "good": 41.0786699107867}, "composites": {"beer_points": 4.949624060150376, "quality_points": 5.2821813570069756, "beer_percentiles": 40.670859538784065, "quality_percentiles": 35.744234800838576}}