{"info": {"language": "Engelsk", "ECTS": 5, "time": "August", "level": "Kandidat", "name": "Syntese i elektroteknologi", "course_no": "31908"}, "evals": [{"time": "F-18-03AUG", "N_responses": 1, "learning_answers": [1, 0, 0, 0, 0], "participation_answers": [1, 0, 0, 0, 0], "material_answers": [1, 0, 0, 0, 0], "clear_answers": [1, 0, 0, 0, 0], "connection_answers": [1, 0, 0, 0, 0], "worklevel_answers": [0, 0, 0, 1, 0], "prerequisite_answers": [0, 0, 1, 0, 0], "good_answers": [1, 0, 0, 0, 0]}], "eval_points": [{"time": "F-18-03AUG", "learning": 4.0, "worklevel": 3.0, "good": 4.0, "N": 1}], "course_no": "31908", "grade_percentile": 51.932367149758456, "eval_percentiles": {"learning": 74.54036770583534, "worklevel": 47.721822541966425, "good": 81.49480415667466}, "composites": {"beer_points": 67.32917189365656, "quality_points": 71.36029631399724, "beer_percentiles": 53.91949152542373, "quality_percentiles": 73.94067796610169}}