{"info": {"language": "Danish", "ECTS": 5, "time": "Autumn E4A (Tues 13-17)", "level": "BSc", "name": "Digital Hardwaredesign for Communications", "course_no": "34331"}, "course_no": "34331", "grade_percentile": 25.95307917888563, "eval_percentiles": {"learning": 78.79581151832461, "worklevel": 83.0715532286213, "good": 34.467713787085515}, "composites": {"beer_points": 4.274406332453826, "quality_points": 5.368975903614457, "beer_percentiles": 15.290697674418604, "quality_percentiles": 36.27906976744186}}