{"info": {"language": "Engelsk", "ECTS": 5, "time": "F4A (tirs 13-17)", "level": "Kandidat", "name": "Optiske netv\u00e6rk", "course_no": "34361"}, "evals": [{"time": "F-19-13", "N_responses": 4, "learning_answers": [1, 1, 2, 0, 0], "participation_answers": [1, 1, 1, 0, 1], "material_answers": [1, 2, 0, 1, 0], "clear_answers": [1, 1, 1, 0, 1], "connection_answers": [0, 2, 1, 0, 1], "worklevel_answers": [0, 0, 3, 0, 1], "prerequisite_answers": [0, 0, 2, 2, 0], "good_answers": [1, 1, 1, 1, 0]}, {"time": "F-17-13", "N_responses": 4, "learning_answers": [0, 2, 1, 0, 1], "participation_answers": [1, 1, 1, 1, 0], "material_answers": [0, 1, 1, 2, 0], "clear_answers": [0, 1, 2, 1, 0], "connection_answers": [0, 2, 1, 1, 0], "worklevel_answers": [0, 1, 1, 1, 1], "prerequisite_answers": [0, 0, 2, 1, 0], "good_answers": [0, 1, 1, 1, 1]}], "eval_points": [{"time": "F-19-13", "learning": 2.75, "worklevel": 2.5, "good": 2.5, "N": 4}, {"time": "F-17-13", "learning": 2.0, "worklevel": 2.5, "good": 1.5, "N": 4}], "grades": [{"time": "2018summer", "N_exam": 10, "N_passed": 10, "exam_avg": 7.3, "grade_dist": [0, 3, 5, 2, 0, 0, 0, 5]}], "course_no": "34361", "grade_percentile": 65.70048309178743, "eval_percentiles": {"learning": 83.49320543565148, "worklevel": 23.26139088729017, "good": 84.65227817745803}, "composites": {"beer_points": 72.44139473723985, "quality_points": 78.43359818388194, "beer_percentiles": 67.69067796610169, "quality_percentiles": 86.22881355932203}}