{"info": {"language": "Engelsk", "ECTS": 5, "time": "F1B (tors 13-17)", "level": "Kandidat", "name": "Robust Design af Produkter og mekanismer", "course_no": "41635"}, "course_no": "41635", "grade_percentile": 9.391304347826088, "eval_percentiles": {"learning": 59.17361637604245, "worklevel": 46.36087945413192, "good": 44.69294920394238}, "composites": {"beer_points": 4.092307692307693, "quality_points": 4.919171096886186, "beer_percentiles": 21.860019175455417, "quality_percentiles": 33.26941514860978}}