{"info": {"language": "Dansk", "ECTS": 5, "time": "F4A (tirs 13-17)", "level": "Bachelor", "name": "Brugerinvolverende systemdesign", "course_no": "42042"}, "evals": [{"time": "F-19-13", "N_responses": 44, "learning_answers": [7, 16, 15, 4, 2], "participation_answers": [21, 14, 6, 2, 1], "material_answers": [8, 11, 15, 5, 5], "clear_answers": [3, 6, 18, 15, 2], "connection_answers": [13, 16, 11, 2, 2], "worklevel_answers": [1, 2, 34, 6, 1], "prerequisite_answers": [1, 1, 40, 1, 1], "good_answers": [10, 12, 14, 6, 2]}, {"time": "F-18-13", "N_responses": 25, "learning_answers": [1, 10, 9, 3, 2], "participation_answers": [4, 15, 2, 2, 2], "material_answers": [2, 5, 9, 5, 3], "clear_answers": [2, 4, 9, 9, 1], "connection_answers": [6, 12, 4, 2, 1], "worklevel_answers": [0, 3, 16, 4, 2], "prerequisite_answers": [1, 2, 22, 0, 0], "good_answers": [2, 13, 5, 5, 0]}, {"time": "F-17-13", "N_responses": 33, "learning_answers": [5, 15, 8, 5, 0], "participation_answers": [15, 11, 3, 4, 0], "material_answers": [6, 15, 6, 5, 1], "clear_answers": [0, 2, 17, 11, 3], "connection_answers": [8, 15, 8, 2, 0], "worklevel_answers": [0, 4, 15, 12, 2], "prerequisite_answers": [0, 1, 31, 0, 0], "good_answers": [10, 11, 7, 5, 0]}, {"time": "F-16-13", "N_responses": 17, "learning_answers": [4, 5, 3, 5, 0], "participation_answers": [5, 5, 5, 2, 0], "material_answers": [1, 6, 6, 4, 0], "clear_answers": [3, 3, 7, 4, 0], "connection_answers": [3, 5, 6, 3, 0], "worklevel_answers": [0, 0, 12, 4, 1], "prerequisite_answers": [0, 0, 17, 0, 0], "good_answers": [3, 8, 2, 3, 1]}, {"time": "F-15-13", "N_responses": 16, "learning_answers": [0, 7, 6, 3, 0], "participation_answers": [2, 11, 3, 0, 0], "material_answers": [0, 3, 6, 3, 4], "clear_answers": [0, 2, 8, 5, 1], "connection_answers": [0, 7, 5, 4, 0], "worklevel_answers": [0, 1, 12, 3, 0], "prerequisite_answers": [0, 0, 15, 1, 0], "good_answers": [1, 7, 7, 0, 0]}, {"time": "F-14-13", "N_responses": 32, "learning_answers": [5, 12, 10, 3, 2], "participation_answers": [12, 12, 7, 0, 1], "material_answers": [2, 8, 11, 7, 4], "clear_answers": [2, 8, 13, 7, 2], "connection_answers": [6, 13, 9, 2, 2], "worklevel_answers": [1, 5, 14, 8, 4], "prerequisite_answers": [1, 1, 26, 3, 1], "good_answers": [7, 8, 10, 6, 1]}, {"time": "F-13-13", "N_responses": 39, "learning_answers": [6, 22, 7, 4, 0], "participation_answers": [13, 17, 7, 1, 1], "material_answers": [2, 7, 18, 9, 3], "clear_answers": [2, 9, 20, 5, 3], "connection_answers": [3, 21, 12, 3, 0], "worklevel_answers": [0, 3, 25, 7, 3], "prerequisite_answers": [0, 0, 37, 2, 0], "good_answers": [8, 18, 10, 3, 0]}, {"time": "F-12-13", "N_responses": 20, "learning_answers": [2, 7, 6, 5, 0], "participation_answers": [7, 9, 3, 1, 0], "material_answers": [1, 6, 9, 3, 1], "clear_answers": [1, 3, 9, 5, 2], "connection_answers": [2, 10, 4, 3, 1], "worklevel_answers": [0, 0, 13, 6, 1], "prerequisite_answers": [0, 0, 19, 0, 0], "good_answers": [2, 6, 8, 2, 2]}, {"time": "F-11-13", "N_responses": 29, "learning_answers": [2, 7, 11, 6, 3], "participation_answers": [3, 14, 10, 1, 1], "material_answers": [3, 6, 10, 4, 5], "clear_answers": [0, 5, 11, 7, 5], "connection_answers": [2, 9, 15, 0, 3], "worklevel_answers": [0, 1, 21, 6, 1], "prerequisite_answers": [0, 3, 24, 1, 1], "good_answers": [2, 8, 13, 3, 3]}], "eval_points": [{"time": "F-19-13", "learning": 6.25, "worklevel": 5.227272727272727, "good": 6.25, "N": 44}, {"time": "F-18-13", "learning": 5.5, "worklevel": 5.5, "good": 6.2, "N": 25}, {"time": "F-17-13", "learning": 6.515151515151515, "worklevel": 5.909090909090909, "good": 6.969696969696971, "N": 33}, {"time": "F-16-13", "learning": 6.176470588235294, "worklevel": 5.882352941176471, "good": 6.323529411764706, "N": 17}, {"time": "F-15-13", "learning": 5.625, "worklevel": 5.3125, "good": 6.09375, "N": 16}, {"time": "F-14-13", "learning": 6.171875, "worklevel": 5.703125, "good": 6.09375, "N": 32}, {"time": "F-13-13", "learning": 6.923076923076923, "worklevel": 5.512820512820513, "good": 6.987179487179487, "N": 39}, {"time": "F-12-13", "learning": 5.75, "worklevel": 6.0, "good": 5.5, "N": 20}, {"time": "F-11-13", "learning": 4.913793103448276, "worklevel": 5.6034482758620685, "good": 5.258620689655173, "N": 29}], "course_no": "42042", "grade_percentile": 26.455026455026456, "eval_percentiles": {"learning": 87.18535469107552, "worklevel": 21.09077040427155, "good": 79.63386727688787}, "composites": {"beer_points": 5.528571428571429, "quality_points": 6.925246826516219, "beer_percentiles": 54.8792270531401, "quality_percentiles": 80.0}}