{"info": {"language": "Engelsk", "ECTS": 5, "time": "Januar", "level": "Kandidat", "name": "Brint- og br\u00e6ndselscellekemi - eksperimentelt kursus", "course_no": "47302"}, "evals": [{"time": "E-17-03", "N_responses": 7, "learning_answers": [6, 1, 0, 0, 0], "participation_answers": [6, 1, 0, 0, 0], "material_answers": [2, 5, 0, 0, 0], "clear_answers": [4, 3, 0, 0, 0], "connection_answers": [6, 0, 1, 0, 0], "worklevel_answers": [1, 1, 5, 0, 0], "prerequisite_answers": [1, 0, 5, 1, 0], "good_answers": [6, 1, 0, 0, 0]}, {"time": "E-14-03", "N_responses": 2, "learning_answers": [1, 1, 0, 0, 0], "participation_answers": [1, 1, 0, 0, 0], "material_answers": [1, 1, 0, 0, 0], "clear_answers": [1, 0, 1, 0, 0], "connection_answers": [1, 1, 0, 0, 0], "worklevel_answers": [0, 1, 1, 0, 0], "prerequisite_answers": [0, 0, 2, 0, 0], "good_answers": [1, 1, 0, 0, 0]}], "eval_points": [{"time": "E-17-03", "learning": 9.642857142857142, "worklevel": 3.9285714285714284, "good": 9.642857142857142, "N": 7}, {"time": "E-14-03", "learning": 8.75, "worklevel": 3.75, "good": 8.75, "N": 2}], "grades": [{"time": "2013winter", "N_exam": 15, "N_passed": 15, "exam_avg": 10.0, "grade_dist": [0, 1, 0, 0, 0, 0, 0, 14, 0, 1]}, {"time": "2012winter", "N_exam": 15, "N_passed": 15, "exam_avg": 10.0, "grade_dist": [0, 1, 0, 0, 0, 0, 0, 14, 0, 1]}], "course_no": "47302", "grade_percentile": 59.7876269621422, "eval_percentiles": {"learning": 78.00982800982801, "worklevel": 85.91318591318591, "good": 79.77067977067978}, "composites": {"beer_points": 5.006596306068602, "quality_points": 6.984186746987951, "beer_percentiles": 29.188619599578505, "quality_percentiles": 72.07586933614331}}