{"info": {"language": "Engelsk", "ECTS": 5, "time": "Januar  eller  August", "level": "Diplomingeni\u00f8r", "name": "System- og netv\u00e6rkssikkerhed - Projekt", "course_no": "62419"}, "course_no": "62419", "grade_percentile": 42.02192448233861, "eval_percentiles": {"learning": 73.44420600858369, "worklevel": 96.99570815450643, "good": 43.776824034334766}, "composites": {"beer_points": 3.4828496042216353, "quality_points": 5.331278890600924, "beer_percentiles": 7.00354609929078, "quality_percentiles": 32.09219858156028}}