{"info": {"language": "Danish", "ECTS": 5, "time": "Autumn E2A (Mon 13-17)", "level": "BEng", "name": "Signal analysis", "course_no": "62524"}, "grades": [{"time": "2019winter", "N_exam": 30, "N_passed": 30, "exam_avg": 10.1, "grade_dist": [16, 8, 4, 0, 2, 0, 0, 4]}], "course_no": "62524", "grade_percentile": null, "eval_percentiles": {"learning": 13.045375218150086, "worklevel": 92.4956369982548, "good": 27.137870855148343}, "composites": {"beer_points": null, "quality_points": null, "beer_percentiles": null, "quality_percentiles": null}}