{"info": {"language": "Engelsk", "ECTS": 5, "time": "F2B (tors 8-12)", "level": "Diplomingeni\u00f8r", "name": "Digitale reguleringssystemer", "course_no": "62716"}, "evals": [{"time": "F-19-13", "N_responses": 5, "learning_answers": [0, 1, 4, 0, 0], "participation_answers": [0, 2, 2, 0, 1], "material_answers": [0, 1, 3, 1, 0], "clear_answers": [1, 2, 1, 1, 0], "connection_answers": [0, 2, 1, 2, 0], "worklevel_answers": [0, 0, 5, 0, 0], "prerequisite_answers": [0, 1, 4, 0, 0], "good_answers": [1, 2, 1, 1, 0]}, {"time": "F-18-13", "N_responses": 2, "learning_answers": [0, 1, 1, 0, 0], "participation_answers": [0, 0, 0, 1, 1], "material_answers": [0, 0, 1, 0, 1], "clear_answers": [0, 0, 1, 0, 1], "connection_answers": [0, 0, 1, 0, 1], "worklevel_answers": [1, 0, 1, 0, 0], "prerequisite_answers": [0, 0, 2, 0, 0], "good_answers": [0, 0, 2, 0, 0]}, {"time": "F-17-13", "N_responses": 2, "learning_answers": [2, 0, 0, 0, 0], "participation_answers": [2, 0, 0, 0, 0], "material_answers": [2, 0, 0, 0, 0], "clear_answers": [2, 0, 0, 0, 0], "connection_answers": [2, 0, 0, 0, 0], "worklevel_answers": [0, 0, 1, 1, 0], "prerequisite_answers": [0, 0, 2, 0, 0], "good_answers": [2, 0, 0, 0, 0]}, {"time": "F-16-13", "N_responses": 4, "learning_answers": [1, 1, 1, 0, 1], "participation_answers": [0, 1, 1, 0, 2], "material_answers": [1, 1, 0, 0, 2], "clear_answers": [1, 1, 0, 1, 1], "connection_answers": [1, 0, 1, 0, 2], "worklevel_answers": [0, 0, 1, 2, 1], "prerequisite_answers": [1, 0, 3, 0, 0], "good_answers": [1, 1, 0, 0, 2]}], "eval_points": [{"time": "F-19-13", "learning": 5.5, "worklevel": 5.0, "good": 6.5, "N": 5}, {"time": "F-18-13", "learning": 6.25, "worklevel": 2.5, "good": 5.0, "N": 2}, {"time": "F-17-13", "learning": 10.0, "worklevel": 6.25, "good": 10.0, "N": 2}, {"time": "F-16-13", "learning": 5.625, "worklevel": 7.5, "good": 4.375, "N": 4}], "grades": [{"time": "2020summer", "N_exam": 40, "N_passed": 33, "exam_avg": 7.8, "grade_dist": [15, 9, 6, 2, 1, 4, 3, 2, 7]}, {"time": "2019summer", "N_exam": 30, "N_passed": 26, "exam_avg": 7.0, "grade_dist": [10, 5, 2, 5, 4, 3, 1, 3]}, {"time": "2018summer", "N_exam": 25, "N_passed": 24, "exam_avg": 9.2, "grade_dist": [14, 2, 4, 3, 1, 1, 0, 1, 7]}, {"time": "2017summer", "N_exam": 21, "N_passed": 18, "exam_avg": 6.9, "grade_dist": [6, 5, 2, 1, 4, 2, 1, 2, 1]}, {"time": "2016summer", "N_exam": 12, "N_passed": 8, "exam_avg": 6.2, "grade_dist": [6, 0, 0, 1, 1, 3, 1, 7]}], "course_no": "62716", "grade_percentile": 55.03663003663004, "eval_percentiles": {"learning": 10.339123242349048, "worklevel": 56.575682382134, "good": 3.598014888337469}, "composites": {"beer_points": 5.945470536499561, "quality_points": 3.57034795763994, "beer_percentiles": 55.16129032258065, "quality_percentiles": 10.10752688172043}}