{
    "info": {
        "language": "Engelsk",
        "ECTS": 5,
        "time": "F3A (tirs 8-12)",
        "level": "Kandidat",
        "name": "Planning and Scheduling in Manufacturing and Services",
        "course_no": "42459"
    },
    "evals": [
        {
            "time": "F-18-13",
            "N_responses": 41,
            "learning_answers": [
                2,
                10,
                13,
                9,
                7
            ],
            "participation_answers": [
                1,
                10,
                13,
                8,
                9
            ],
            "material_answers": [
                2,
                10,
                13,
                10,
                6
            ],
            "clear_answers": [
                0,
                4,
                10,
                13,
                13
            ],
            "connection_answers": [
                3,
                9,
                13,
                11,
                5
            ],
            "worklevel_answers": [
                1,
                7,
                18,
                10,
                5
            ],
            "prerequisite_answers": [
                0,
                3,
                35,
                2,
                1
            ],
            "good_answers": [
                3,
                9,
                13,
                9,
                7
            ]
        },
        {
            "time": "F-17-13",
            "N_responses": 31,
            "learning_answers": [
                9,
                13,
                4,
                3,
                2
            ],
            "participation_answers": [
                10,
                9,
                6,
                5,
                1
            ],
            "material_answers": [
                9,
                11,
                4,
                5,
                2
            ],
            "clear_answers": [
                8,
                10,
                8,
                4,
                1
            ],
            "connection_answers": [
                12,
                12,
                4,
                2,
                1
            ],
            "worklevel_answers": [
                1,
                3,
                14,
                11,
                2
            ],
            "prerequisite_answers": [
                0,
                3,
                26,
                2,
                0
            ],
            "good_answers": [
                9,
                10,
                5,
                5,
                2
            ]
        },
        {
            "time": "F-16-13",
            "N_responses": 22,
            "learning_answers": [
                5,
                7,
                5,
                3,
                2
            ],
            "participation_answers": [
                5,
                4,
                6,
                5,
                2
            ],
            "material_answers": [
                3,
                4,
                7,
                5,
                3
            ],
            "clear_answers": [
                2,
                5,
                9,
                4,
                2
            ],
            "connection_answers": [
                4,
                7,
                8,
                0,
                2
            ],
            "worklevel_answers": [
                0,
                2,
                10,
                7,
                3
            ],
            "prerequisite_answers": [
                0,
                0,
                21,
                1,
                0
            ],
            "good_answers": [
                5,
                8,
                5,
                2,
                2
            ]
        },
        {
            "time": "F-15-13",
            "N_responses": 14,
            "learning_answers": [
                2,
                5,
                6,
                1,
                0
            ],
            "participation_answers": [
                1,
                9,
                3,
                1,
                0
            ],
            "material_answers": [
                3,
                6,
                5,
                0,
                0
            ],
            "clear_answers": [
                2,
                7,
                3,
                2,
                0
            ],
            "connection_answers": [
                1,
                8,
                5,
                0,
                0
            ],
            "worklevel_answers": [
                1,
                2,
                6,
                3,
                2
            ],
            "prerequisite_answers": [
                0,
                1,
                10,
                1,
                2
            ],
            "good_answers": [
                2,
                9,
                3,
                0,
                0
            ]
        }
    ],
    "eval_points": [
        {
            "time": "F-18-13",
            "learning": 2.7804878048780486,
            "worklevel": 3.268292682926829,
            "good": 2.8048780487804876,
            "N": 41
        },
        {
            "time": "F-17-13",
            "learning": 3.774193548387097,
            "worklevel": 3.3225806451612905,
            "good": 3.6129032258064515,
            "N": 31
        },
        {
            "time": "F-16-13",
            "learning": 3.4545454545454546,
            "worklevel": 3.5,
            "good": 3.5454545454545454,
            "N": 22
        },
        {
            "time": "F-15-13",
            "learning": 3.5714285714285716,
            "worklevel": 3.2142857142857144,
            "good": 3.9285714285714284,
            "N": 14
        }
    ],
    "grades": [
        {
            "time": "2017summer",
            "N_exam": 84,
            "N_passed": 84,
            "exam_avg": 9.1,
            "grade_dist": [
                25,
                29,
                20,
                9,
                1,
                0,
                0,
                1,
                10
            ]
        },
        {
            "time": "2016summer",
            "N_exam": 62,
            "N_passed": 59,
            "exam_avg": 8.3,
            "grade_dist": [
                19,
                17,
                12,
                5,
                6,
                3,
                0,
                11
            ]
        },
        {
            "time": "2015summer",
            "N_exam": 65,
            "N_passed": 65,
            "exam_avg": 10.4,
            "grade_dist": [
                39,
                14,
                7,
                4,
                1,
                0,
                0,
                5
            ]
        },
        {
            "time": "2014summer",
            "N_exam": 38,
            "N_passed": 38,
            "exam_avg": 10.8,
            "grade_dist": [
                24,
                8,
                6,
                0,
                0,
                0,
                0,
                2
            ]
        },
        {
            "time": "2013summer",
            "N_exam": 52,
            "N_passed": 52,
            "exam_avg": 9.5,
            "grade_dist": [
                5,
                37,
                9,
                0,
                1,
                0,
                0,
                3
            ]
        },
        {
            "time": "2012summer",
            "N_exam": 32,
            "N_passed": 32,
            "exam_avg": 9.0,
            "grade_dist": [
                6,
                11,
                15,
                0,
                0,
                0,
                0,
                2
            ]
        },
        {
            "time": "2011summer",
            "N_exam": 40,
            "N_passed": 40,
            "exam_avg": 9.6,
            "grade_dist": [
                18,
                8,
                11,
                3,
                0,
                0,
                0,
                1
            ]
        },
        {
            "time": "2010summer",
            "N_exam": 15,
            "N_passed": 15,
            "exam_avg": 9.8,
            "grade_dist": [
                5,
                4,
                4,
                0,
                0,
                0,
                0,
                2,
                0,
                1
            ]
        }
    ],
    "grade_percentile": 75.398313027179,
    "eval_percentiles": {
        "learning": 4.361617763679619,
        "worklevel": 60.42823156225218,
        "good": 8.564631245043616
    },
    "composites": {
        "beer_points": 2.438045486098855,
        "quality_points": 2.1677067720397867,
        "beer_percentiles": 66.66666666666667,
        "quality_percentiles": 34.83483483483484
    }
}