{
    "info": {
        "language": "Engelsk",
        "ECTS": 5,
        "time": "E5A (ons 8-12)",
        "level": "Kandidat",
        "name": "Avancerede metoder til computersimuleringer af energimaterialer",
        "course_no": "47316"
    },
    "evals": [
        {
            "time": "E-17-13",
            "N_responses": 7,
            "learning_answers": [
                2,
                3,
                1,
                1,
                0
            ],
            "participation_answers": [
                3,
                2,
                2,
                0,
                0
            ],
            "material_answers": [
                2,
                1,
                1,
                2,
                1
            ],
            "clear_answers": [
                1,
                2,
                2,
                1,
                1
            ],
            "connection_answers": [
                3,
                2,
                1,
                1,
                0
            ],
            "worklevel_answers": [
                0,
                1,
                4,
                2,
                0
            ],
            "prerequisite_answers": [
                0,
                2,
                3,
                1,
                0
            ],
            "good_answers": [
                2,
                3,
                1,
                1,
                0
            ]
        },
        {
            "time": "E-16-13",
            "N_responses": 12,
            "learning_answers": [
                7,
                2,
                2,
                1,
                0
            ],
            "participation_answers": [
                6,
                4,
                0,
                2,
                0
            ],
            "material_answers": [
                7,
                1,
                2,
                1,
                1
            ],
            "clear_answers": [
                6,
                2,
                3,
                0,
                1
            ],
            "connection_answers": [
                5,
                3,
                1,
                2,
                1
            ],
            "worklevel_answers": [
                0,
                3,
                3,
                5,
                1
            ],
            "prerequisite_answers": [
                1,
                0,
                11,
                0,
                0
            ],
            "good_answers": [
                6,
                1,
                3,
                2,
                0
            ]
        },
        {
            "time": "E-15-13",
            "N_responses": 6,
            "learning_answers": [
                3,
                2,
                1,
                0,
                0
            ],
            "participation_answers": [
                5,
                1,
                0,
                0,
                0
            ],
            "material_answers": [
                1,
                2,
                3,
                0,
                0
            ],
            "clear_answers": [
                3,
                1,
                2,
                0,
                0
            ],
            "connection_answers": [
                2,
                4,
                0,
                0,
                0
            ],
            "worklevel_answers": [
                0,
                0,
                3,
                2,
                1
            ],
            "prerequisite_answers": [
                0,
                0,
                5,
                1,
                0
            ],
            "good_answers": [
                3,
                2,
                0,
                0,
                1
            ]
        },
        {
            "time": "E-14-13",
            "N_responses": 4,
            "learning_answers": [
                3,
                1,
                0,
                0,
                0
            ],
            "participation_answers": [
                3,
                0,
                1,
                0,
                0
            ],
            "material_answers": [
                1,
                1,
                2,
                0,
                0
            ],
            "clear_answers": [
                3,
                0,
                1,
                0,
                0
            ],
            "connection_answers": [
                1,
                2,
                1,
                0,
                0
            ],
            "worklevel_answers": [
                0,
                0,
                3,
                0,
                1
            ],
            "prerequisite_answers": [
                0,
                0,
                4,
                0,
                0
            ],
            "good_answers": [
                2,
                2,
                0,
                0,
                0
            ]
        }
    ],
    "eval_points": [
        {
            "time": "E-17-13",
            "learning": 3.857142857142857,
            "worklevel": 3.142857142857143,
            "good": 3.857142857142857,
            "N": 7
        },
        {
            "time": "E-16-13",
            "learning": 4.25,
            "worklevel": 3.3333333333333335,
            "good": 3.9166666666666665,
            "N": 12
        },
        {
            "time": "E-15-13",
            "learning": 4.333333333333333,
            "worklevel": 3.6666666666666665,
            "good": 4.0,
            "N": 6
        },
        {
            "time": "E-14-13",
            "learning": 4.75,
            "worklevel": 3.5,
            "good": 4.5,
            "N": 4
        }
    ],
    "grades": [
        {
            "time": "2018winter",
            "N_exam": 7,
            "N_passed": 7,
            "exam_avg": 9.6,
            "grade_dist": [
                3,
                2,
                1,
                1,
                0,
                0,
                0,
                1
            ]
        },
        {
            "time": "2017winter",
            "N_exam": 11,
            "N_passed": 11,
            "exam_avg": 9.2,
            "grade_dist": [
                3,
                4,
                3,
                1,
                0,
                0,
                0,
                2
            ]
        },
        {
            "time": "2016winter",
            "N_exam": 14,
            "N_passed": 14,
            "exam_avg": 10.6,
            "grade_dist": [
                6,
                7,
                1,
                0,
                0,
                0,
                0,
                1,
                1
            ]
        },
        {
            "time": "2015winter",
            "N_exam": 5,
            "N_passed": 5,
            "exam_avg": 11.2,
            "grade_dist": [
                3,
                2,
                0,
                0,
                0,
                0,
                0,
                4
            ]
        },
        {
            "time": "2014winter",
            "N_exam": 7,
            "N_passed": 7,
            "exam_avg": 10.1,
            "grade_dist": [
                2,
                4,
                1,
                0,
                0,
                0,
                0,
                1
            ]
        }
    ],
    "grade_percentile": 83.7863167760075,
    "eval_percentiles": {
        "learning": 33.70340999206979,
        "worklevel": 50.87232355273592,
        "good": 42.228390166534496
    },
    "composites": {
        "beer_points": 2.6477568740955135,
        "quality_points": 2.9063048683160413,
        "beer_percentiles": 78.67867867867868,
        "quality_percentiles": 77.57757757757757
    }
}