{
    "info": {
        "language": "Engelsk",
        "ECTS": 5,
        "time": "E5B (ons 13-17)  eller  F5B (ons 13-17)",
        "level": "Diplomingeni\u00f8r",
        "name": "Avanceret objektorienteret programmering med C# og .NET",
        "course_no": "62413"
    },
    "evals": [
        {
            "time": "F-19-13",
            "N_responses": 15,
            "learning_answers": [
                2,
                4,
                4,
                2,
                3
            ],
            "participation_answers": [
                3,
                3,
                1,
                4,
                4
            ],
            "material_answers": [
                2,
                0,
                7,
                3,
                3
            ],
            "clear_answers": [
                3,
                2,
                2,
                1,
                7
            ],
            "connection_answers": [
                3,
                2,
                2,
                5,
                3
            ],
            "worklevel_answers": [
                0,
                2,
                7,
                5,
                1
            ],
            "prerequisite_answers": [
                1,
                0,
                13,
                0,
                1
            ],
            "good_answers": [
                3,
                2,
                5,
                3,
                2
            ]
        },
        {
            "time": "E-18-13",
            "N_responses": 3,
            "learning_answers": [
                1,
                0,
                1,
                1,
                0
            ],
            "participation_answers": [
                0,
                1,
                1,
                0,
                1
            ],
            "material_answers": [
                1,
                0,
                1,
                1,
                0
            ],
            "clear_answers": [
                0,
                1,
                0,
                2,
                0
            ],
            "connection_answers": [
                1,
                1,
                0,
                1,
                0
            ],
            "worklevel_answers": [
                0,
                0,
                3,
                0,
                0
            ],
            "prerequisite_answers": [
                0,
                0,
                3,
                0,
                0
            ],
            "good_answers": [
                1,
                1,
                0,
                1,
                0
            ]
        },
        {
            "time": "F-18-13",
            "N_responses": 5,
            "learning_answers": [
                0,
                0,
                2,
                3,
                0
            ],
            "participation_answers": [
                2,
                0,
                2,
                1,
                0
            ],
            "material_answers": [
                0,
                2,
                0,
                2,
                1
            ],
            "clear_answers": [
                1,
                1,
                0,
                2,
                1
            ],
            "connection_answers": [
                0,
                3,
                0,
                1,
                1
            ],
            "worklevel_answers": [
                1,
                1,
                3,
                0,
                0
            ],
            "prerequisite_answers": [
                0,
                1,
                4,
                0,
                0
            ],
            "good_answers": [
                1,
                1,
                0,
                3,
                0
            ]
        },
        {
            "time": "E-17-13",
            "N_responses": 2,
            "learning_answers": [
                0,
                0,
                1,
                1,
                0
            ],
            "participation_answers": [
                0,
                1,
                0,
                0,
                1
            ],
            "material_answers": [
                1,
                1,
                0,
                0,
                0
            ],
            "clear_answers": [
                0,
                1,
                0,
                1,
                0
            ],
            "connection_answers": [
                0,
                1,
                0,
                1,
                0
            ],
            "worklevel_answers": [
                0,
                1,
                1,
                0,
                0
            ],
            "prerequisite_answers": [
                0,
                0,
                2,
                0,
                0
            ],
            "good_answers": [
                0,
                1,
                1,
                0,
                0
            ]
        }
    ],
    "eval_points": [
        {
            "time": "F-19-13",
            "learning": 3.0,
            "worklevel": 3.3333333333333335,
            "good": 3.066666666666667,
            "N": 15
        },
        {
            "time": "E-18-13",
            "learning": 3.3333333333333335,
            "worklevel": 3.0,
            "good": 3.6666666666666665,
            "N": 3
        },
        {
            "time": "F-18-13",
            "learning": 2.4,
            "worklevel": 2.4,
            "good": 3.0,
            "N": 5
        },
        {
            "time": "E-17-13",
            "learning": 2.5,
            "worklevel": 2.5,
            "good": 3.5,
            "N": 2
        }
    ],
    "grades": [
        {
            "time": "2019summer",
            "N_exam": 73,
            "N_passed": 73,
            "exam_avg": 8.8,
            "grade_dist": [
                19,
                24,
                18,
                11,
                1,
                0,
                0,
                19
            ]
        },
        {
            "time": "2018summer",
            "N_exam": 22,
            "N_passed": 22,
            "exam_avg": 8.1,
            "grade_dist": [
                3,
                8,
                6,
                5,
                0,
                0,
                0,
                4
            ]
        },
        {
            "time": "2018winter",
            "N_exam": 28,
            "N_passed": 28,
            "exam_avg": 9.1,
            "grade_dist": [
                8,
                10,
                7,
                2,
                1,
                0,
                0,
                7
            ]
        },
        {
            "time": "2017winter",
            "N_exam": 14,
            "N_passed": 14,
            "exam_avg": 8.2,
            "grade_dist": [
                3,
                4,
                5,
                0,
                2,
                0,
                0,
                4
            ]
        }
    ],
    "grade_percentile": 68.50984067478913,
    "eval_percentiles": {
        "learning": 7.454401268834259,
        "worklevel": 64.90880253766852,
        "good": 13.203806502775574
    },
    "composites": {
        "beer_points": 3.320501688374337,
        "quality_points": 3.1988826815642453,
        "beer_percentiles": 58.75875875875876,
        "quality_percentiles": 36.53653653653654
    }
}